{
  "summary": {
    "total_files": 103,
    "successful_files": 103,
    "failed_files": 0,
    "overall_elapsed_time": 3880.52876830101,
    "total_spark_time": 2769.233903646469,
    "overhead": 1111.294864654541,
    "overhead_percentage": 28.637717460888528,
    "config_idx": 1,
    "fidelity": 0.1,
    "database": "tpcds_100g",
    "config": {
      "spark.default.parallelism": 1156,
      "spark.driver.cores": 12,
      "spark.driver.maxResultSize": 4096,
      "spark.driver.memory": 34,
      "spark.executor.cores": 12,
      "spark.executor.instances": 18,
      "spark.executor.memory": 180,
      "spark.executor.memoryOverhead": 6741,
      "spark.locality.wait": 0,
      "spark.network.timeout": 11593,
      "spark.scheduler.minRegisteredResourcesRatio": 0.8500000000000001,
      "spark.sql.autoBroadcastJoinThreshold": 373,
      "spark.sql.broadcastTimeout": 21377,
      "spark.sql.shuffle.partitions": 1091,
      "spark.sql.sources.parallelPartitionDiscovery.parallelism": 112,
      "spark.task.cpus": 2
    }
  },
  "results": [
    {
      "sql_file": "q10",
      "total_elapsed_time": 40.473591804504395,
      "query_count": 1,
      "queries": [
        {
          "query_index": 0,
          "query": "q10_0",
          "elapsed_time": 28.748825073242188,
          "status": "success"
        }
      ],
      "status": "success"
    },
    {
      "sql_file": "q11",
      "total_elapsed_time": 57.307941198349,
      "query_count": 1,
      "queries": [
        {
          "query_index": 0,
          "query": "q11_0",
          "elapsed_time": 46.886457681655884,
          "status": "success"
        }
      ],
      "status": "success"
    },
    {
      "sql_file": "q12",
      "total_elapsed_time": 15.187104225158691,
      "query_count": 1,
      "queries": [
        {
          "query_index": 0,
          "query": "q12_0",
          "elapsed_time": 4.2334911823272705,
          "status": "success"
        }
      ],
      "status": "success"
    },
    {
      "sql_file": "q13",
      "total_elapsed_time": 20.756139993667603,
      "query_count": 1,
      "queries": [
        {
          "query_index": 0,
          "query": "q13_0",
          "elapsed_time": 10.695902347564697,
          "status": "success"
        }
      ],
      "status": "success"
    },
    {
      "sql_file": "q14a",
      "total_elapsed_time": 88.20219802856445,
      "query_count": 1,
      "queries": [
        {
          "query_index": 0,
          "query": "q14a_0",
          "elapsed_time": 78.13318419456482,
          "status": "success"
        }
      ],
      "status": "success"
    },
    {
      "sql_file": "q14b",
      "total_elapsed_time": 79.83435893058777,
      "query_count": 1,
      "queries": [
        {
          "query_index": 0,
          "query": "q14b_0",
          "elapsed_time": 67.86547780036926,
          "status": "success"
        }
      ],
      "status": "success"
    },
    {
      "sql_file": "q15",
      "total_elapsed_time": 16.868617057800293,
      "query_count": 1,
      "queries": [
        {
          "query_index": 0,
          "query": "q15_0",
          "elapsed_time": 4.803805112838745,
          "status": "success"
        }
      ],
      "status": "success"
    },
    {
      "sql_file": "q16",
      "total_elapsed_time": 79.31823658943176,
      "query_count": 1,
      "queries": [
        {
          "query_index": 0,
          "query": "q16_0",
          "elapsed_time": 69.34373807907104,
          "status": "success"
        }
      ],
      "status": "success"
    },
    {
      "sql_file": "q17",
      "total_elapsed_time": 30.99027681350708,
      "query_count": 1,
      "queries": [
        {
          "query_index": 0,
          "query": "q17_0",
          "elapsed_time": 18.815839052200317,
          "status": "success"
        }
      ],
      "status": "success"
    },
    {
      "sql_file": "q18",
      "total_elapsed_time": 19.184495449066162,
      "query_count": 1,
      "queries": [
        {
          "query_index": 0,
          "query": "q18_0",
          "elapsed_time": 8.806808471679688,
          "status": "success"
        }
      ],
      "status": "success"
    },
    {
      "sql_file": "q19",
      "total_elapsed_time": 14.616421222686768,
      "query_count": 1,
      "queries": [
        {
          "query_index": 0,
          "query": "q19_0",
          "elapsed_time": 4.5193891525268555,
          "status": "success"
        }
      ],
      "status": "success"
    },
    {
      "sql_file": "q1",
      "total_elapsed_time": 22.822981119155884,
      "query_count": 1,
      "queries": [
        {
          "query_index": 0,
          "query": "q1_0",
          "elapsed_time": 12.398784160614014,
          "status": "success"
        }
      ],
      "status": "success"
    },
    {
      "sql_file": "q20",
      "total_elapsed_time": 13.020325899124146,
      "query_count": 1,
      "queries": [
        {
          "query_index": 0,
          "query": "q20_0",
          "elapsed_time": 2.9053924083709717,
          "status": "success"
        }
      ],
      "status": "success"
    },
    {
      "sql_file": "q21",
      "total_elapsed_time": 12.696563720703125,
      "query_count": 1,
      "queries": [
        {
          "query_index": 0,
          "query": "q21_0",
          "elapsed_time": 2.7681989669799805,
          "status": "success"
        }
      ],
      "status": "success"
    },
    {
      "sql_file": "q22",
      "total_elapsed_time": 32.73668432235718,
      "query_count": 1,
      "queries": [
        {
          "query_index": 0,
          "query": "q22_0",
          "elapsed_time": 22.894460439682007,
          "status": "success"
        }
      ],
      "status": "success"
    },
    {
      "sql_file": "q23a",
      "total_elapsed_time": 126.31413912773132,
      "query_count": 1,
      "queries": [
        {
          "query_index": 0,
          "query": "q23a_0",
          "elapsed_time": 115.80259490013123,
          "status": "success"
        }
      ],
      "status": "success"
    },
    {
      "sql_file": "q23b",
      "total_elapsed_time": 144.73990893363953,
      "query_count": 1,
      "queries": [
        {
          "query_index": 0,
          "query": "q23b_0",
          "elapsed_time": 131.80306386947632,
          "status": "success"
        }
      ],
      "status": "success"
    },
    {
      "sql_file": "q24a",
      "total_elapsed_time": 110.30725073814392,
      "query_count": 1,
      "queries": [
        {
          "query_index": 0,
          "query": "q24a_0",
          "elapsed_time": 97.54989528656006,
          "status": "success"
        }
      ],
      "status": "success"
    },
    {
      "sql_file": "q24b",
      "total_elapsed_time": 107.67474317550659,
      "query_count": 1,
      "queries": [
        {
          "query_index": 0,
          "query": "q24b_0",
          "elapsed_time": 94.08961129188538,
          "status": "success"
        }
      ],
      "status": "success"
    },
    {
      "sql_file": "q25",
      "total_elapsed_time": 28.219316005706787,
      "query_count": 1,
      "queries": [
        {
          "query_index": 0,
          "query": "q25_0",
          "elapsed_time": 14.745838642120361,
          "status": "success"
        }
      ],
      "status": "success"
    },
    {
      "sql_file": "q26",
      "total_elapsed_time": 16.216599464416504,
      "query_count": 1,
      "queries": [
        {
          "query_index": 0,
          "query": "q26_0",
          "elapsed_time": 5.929908037185669,
          "status": "success"
        }
      ],
      "status": "success"
    },
    {
      "sql_file": "q27",
      "total_elapsed_time": 16.56176733970642,
      "query_count": 1,
      "queries": [
        {
          "query_index": 0,
          "query": "q27_0",
          "elapsed_time": 6.379853248596191,
          "status": "success"
        }
      ],
      "status": "success"
    },
    {
      "sql_file": "q28",
      "total_elapsed_time": 89.95135879516602,
      "query_count": 1,
      "queries": [
        {
          "query_index": 0,
          "query": "q28_0",
          "elapsed_time": 79.4438853263855,
          "status": "success"
        }
      ],
      "status": "success"
    },
    {
      "sql_file": "q29",
      "total_elapsed_time": 43.361512660980225,
      "query_count": 1,
      "queries": [
        {
          "query_index": 0,
          "query": "q29_0",
          "elapsed_time": 30.091684579849243,
          "status": "success"
        }
      ],
      "status": "success"
    },
    {
      "sql_file": "q2",
      "total_elapsed_time": 32.6727614402771,
      "query_count": 1,
      "queries": [
        {
          "query_index": 0,
          "query": "q2_0",
          "elapsed_time": 21.498249530792236,
          "status": "success"
        }
      ],
      "status": "success"
    },
    {
      "sql_file": "q30",
      "total_elapsed_time": 22.952243328094482,
      "query_count": 1,
      "queries": [
        {
          "query_index": 0,
          "query": "q30_0",
          "elapsed_time": 11.951022148132324,
          "status": "success"
        }
      ],
      "status": "success"
    },
    {
      "sql_file": "q31",
      "total_elapsed_time": 20.84011721611023,
      "query_count": 1,
      "queries": [
        {
          "query_index": 0,
          "query": "q31_0",
          "elapsed_time": 10.845775842666626,
          "status": "success"
        }
      ],
      "status": "success"
    },
    {
      "sql_file": "q32",
      "total_elapsed_time": 13.434450387954712,
      "query_count": 1,
      "queries": [
        {
          "query_index": 0,
          "query": "q32_0",
          "elapsed_time": 3.3680410385131836,
          "status": "success"
        }
      ],
      "status": "success"
    },
    {
      "sql_file": "q33",
      "total_elapsed_time": 14.776703834533691,
      "query_count": 1,
      "queries": [
        {
          "query_index": 0,
          "query": "q33_0",
          "elapsed_time": 4.720944404602051,
          "status": "success"
        }
      ],
      "status": "success"
    },
    {
      "sql_file": "q34",
      "total_elapsed_time": 15.749378442764282,
      "query_count": 1,
      "queries": [
        {
          "query_index": 0,
          "query": "q34_0",
          "elapsed_time": 5.779312610626221,
          "status": "success"
        }
      ],
      "status": "success"
    },
    {
      "sql_file": "q35",
      "total_elapsed_time": 27.97651219367981,
      "query_count": 1,
      "queries": [
        {
          "query_index": 0,
          "query": "q35_0",
          "elapsed_time": 17.97068691253662,
          "status": "success"
        }
      ],
      "status": "success"
    },
    {
      "sql_file": "q36",
      "total_elapsed_time": 16.438518047332764,
      "query_count": 1,
      "queries": [
        {
          "query_index": 0,
          "query": "q36_0",
          "elapsed_time": 6.44388484954834,
          "status": "success"
        }
      ],
      "status": "success"
    },
    {
      "sql_file": "q37",
      "total_elapsed_time": 27.846388816833496,
      "query_count": 1,
      "queries": [
        {
          "query_index": 0,
          "query": "q37_0",
          "elapsed_time": 17.712656259536743,
          "status": "success"
        }
      ],
      "status": "success"
    },
    {
      "sql_file": "q38",
      "total_elapsed_time": 34.24927735328674,
      "query_count": 1,
      "queries": [
        {
          "query_index": 0,
          "query": "q38_0",
          "elapsed_time": 23.634626388549805,
          "status": "success"
        }
      ],
      "status": "success"
    },
    {
      "sql_file": "q39a",
      "total_elapsed_time": 18.63204860687256,
      "query_count": 1,
      "queries": [
        {
          "query_index": 0,
          "query": "q39a_0",
          "elapsed_time": 7.945035934448242,
          "status": "success"
        }
      ],
      "status": "success"
    },
    {
      "sql_file": "q39b",
      "total_elapsed_time": 16.77444553375244,
      "query_count": 1,
      "queries": [
        {
          "query_index": 0,
          "query": "q39b_0",
          "elapsed_time": 6.849439382553101,
          "status": "success"
        }
      ],
      "status": "success"
    },
    {
      "sql_file": "q3",
      "total_elapsed_time": 13.38288950920105,
      "query_count": 1,
      "queries": [
        {
          "query_index": 0,
          "query": "q3_0",
          "elapsed_time": 3.3982372283935547,
          "status": "success"
        }
      ],
      "status": "success"
    },
    {
      "sql_file": "q40",
      "total_elapsed_time": 23.05047845840454,
      "query_count": 1,
      "queries": [
        {
          "query_index": 0,
          "query": "q40_0",
          "elapsed_time": 12.966926574707031,
          "status": "success"
        }
      ],
      "status": "success"
    },
    {
      "sql_file": "q41",
      "total_elapsed_time": 11.532268285751343,
      "query_count": 1,
      "queries": [
        {
          "query_index": 0,
          "query": "q41_0",
          "elapsed_time": 1.3157508373260498,
          "status": "success"
        }
      ],
      "status": "success"
    },
    {
      "sql_file": "q42",
      "total_elapsed_time": 12.027134895324707,
      "query_count": 1,
      "queries": [
        {
          "query_index": 0,
          "query": "q42_0",
          "elapsed_time": 2.101149082183838,
          "status": "success"
        }
      ],
      "status": "success"
    },
    {
      "sql_file": "q43",
      "total_elapsed_time": 15.165921211242676,
      "query_count": 1,
      "queries": [
        {
          "query_index": 0,
          "query": "q43_0",
          "elapsed_time": 5.203150510787964,
          "status": "success"
        }
      ],
      "status": "success"
    },
    {
      "sql_file": "q44",
      "total_elapsed_time": 31.630183458328247,
      "query_count": 1,
      "queries": [
        {
          "query_index": 0,
          "query": "q44_0",
          "elapsed_time": 21.653658866882324,
          "status": "success"
        }
      ],
      "status": "success"
    },
    {
      "sql_file": "q45",
      "total_elapsed_time": 15.87090015411377,
      "query_count": 1,
      "queries": [
        {
          "query_index": 0,
          "query": "q45_0",
          "elapsed_time": 4.724333047866821,
          "status": "success"
        }
      ],
      "status": "success"
    },
    {
      "sql_file": "q46",
      "total_elapsed_time": 16.493048667907715,
      "query_count": 1,
      "queries": [
        {
          "query_index": 0,
          "query": "q46_0",
          "elapsed_time": 6.464749097824097,
          "status": "success"
        }
      ],
      "status": "success"
    },
    {
      "sql_file": "q47",
      "total_elapsed_time": 24.110008239746094,
      "query_count": 1,
      "queries": [
        {
          "query_index": 0,
          "query": "q47_0",
          "elapsed_time": 14.106484413146973,
          "status": "success"
        }
      ],
      "status": "success"
    },
    {
      "sql_file": "q48",
      "total_elapsed_time": 17.806396484375,
      "query_count": 1,
      "queries": [
        {
          "query_index": 0,
          "query": "q48_0",
          "elapsed_time": 7.559933423995972,
          "status": "success"
        }
      ],
      "status": "success"
    },
    {
      "sql_file": "q49",
      "total_elapsed_time": 34.88487887382507,
      "query_count": 1,
      "queries": [
        {
          "query_index": 0,
          "query": "q49_0",
          "elapsed_time": 24.913604736328125,
          "status": "success"
        }
      ],
      "status": "success"
    },
    {
      "sql_file": "q4",
      "total_elapsed_time": 115.24793481826782,
      "query_count": 1,
      "queries": [
        {
          "query_index": 0,
          "query": "q4_0",
          "elapsed_time": 104.60526585578918,
          "status": "success"
        }
      ],
      "status": "success"
    },
    {
      "sql_file": "q50",
      "total_elapsed_time": 29.94310712814331,
      "query_count": 1,
      "queries": [
        {
          "query_index": 0,
          "query": "q50_0",
          "elapsed_time": 17.924262523651123,
          "status": "success"
        }
      ],
      "status": "success"
    },
    {
      "sql_file": "q51",
      "total_elapsed_time": 51.9428448677063,
      "query_count": 1,
      "queries": [
        {
          "query_index": 0,
          "query": "q51_0",
          "elapsed_time": 41.17882466316223,
          "status": "success"
        }
      ],
      "status": "success"
    },
    {
      "sql_file": "q52",
      "total_elapsed_time": 13.59400749206543,
      "query_count": 1,
      "queries": [
        {
          "query_index": 0,
          "query": "q52_0",
          "elapsed_time": 2.388225555419922,
          "status": "success"
        }
      ],
      "status": "success"
    },
    {
      "sql_file": "q53",
      "total_elapsed_time": 15.421335935592651,
      "query_count": 1,
      "queries": [
        {
          "query_index": 0,
          "query": "q53_0",
          "elapsed_time": 5.384186744689941,
          "status": "success"
        }
      ],
      "status": "success"
    },
    {
      "sql_file": "q54",
      "total_elapsed_time": 20.671125650405884,
      "query_count": 1,
      "queries": [
        {
          "query_index": 0,
          "query": "q54_0",
          "elapsed_time": 10.513304710388184,
          "status": "success"
        }
      ],
      "status": "success"
    },
    {
      "sql_file": "q55",
      "total_elapsed_time": 12.2645742893219,
      "query_count": 1,
      "queries": [
        {
          "query_index": 0,
          "query": "q55_0",
          "elapsed_time": 2.0980095863342285,
          "status": "success"
        }
      ],
      "status": "success"
    },
    {
      "sql_file": "q56",
      "total_elapsed_time": 14.370298624038696,
      "query_count": 1,
      "queries": [
        {
          "query_index": 0,
          "query": "q56_0",
          "elapsed_time": 4.435002326965332,
          "status": "success"
        }
      ],
      "status": "success"
    },
    {
      "sql_file": "q57",
      "total_elapsed_time": 22.572091817855835,
      "query_count": 1,
      "queries": [
        {
          "query_index": 0,
          "query": "q57_0",
          "elapsed_time": 12.649095058441162,
          "status": "success"
        }
      ],
      "status": "success"
    },
    {
      "sql_file": "q58",
      "total_elapsed_time": 15.337407350540161,
      "query_count": 1,
      "queries": [
        {
          "query_index": 0,
          "query": "q58_0",
          "elapsed_time": 4.9102582931518555,
          "status": "success"
        }
      ],
      "status": "success"
    },
    {
      "sql_file": "q59",
      "total_elapsed_time": 35.21855640411377,
      "query_count": 1,
      "queries": [
        {
          "query_index": 0,
          "query": "q59_0",
          "elapsed_time": 25.263747453689575,
          "status": "success"
        }
      ],
      "status": "success"
    },
    {
      "sql_file": "q5",
      "total_elapsed_time": 24.562103748321533,
      "query_count": 1,
      "queries": [
        {
          "query_index": 0,
          "query": "q5_0",
          "elapsed_time": 13.496711254119873,
          "status": "success"
        }
      ],
      "status": "success"
    },
    {
      "sql_file": "q60",
      "total_elapsed_time": 16.12026309967041,
      "query_count": 1,
      "queries": [
        {
          "query_index": 0,
          "query": "q60_0",
          "elapsed_time": 5.776762008666992,
          "status": "success"
        }
      ],
      "status": "success"
    },
    {
      "sql_file": "q61",
      "total_elapsed_time": 15.27915358543396,
      "query_count": 1,
      "queries": [
        {
          "query_index": 0,
          "query": "q61_0",
          "elapsed_time": 5.2486326694488525,
          "status": "success"
        }
      ],
      "status": "success"
    },
    {
      "sql_file": "q62",
      "total_elapsed_time": 17.822826623916626,
      "query_count": 1,
      "queries": [
        {
          "query_index": 0,
          "query": "q62_0",
          "elapsed_time": 7.806422472000122,
          "status": "success"
        }
      ],
      "status": "success"
    },
    {
      "sql_file": "q63",
      "total_elapsed_time": 14.821185111999512,
      "query_count": 1,
      "queries": [
        {
          "query_index": 0,
          "query": "q63_0",
          "elapsed_time": 4.724323511123657,
          "status": "success"
        }
      ],
      "status": "success"
    },
    {
      "sql_file": "q64",
      "total_elapsed_time": 84.32461428642273,
      "query_count": 1,
      "queries": [
        {
          "query_index": 0,
          "query": "q64_0",
          "elapsed_time": 74.26661539077759,
          "status": "success"
        }
      ],
      "status": "success"
    },
    {
      "sql_file": "q65",
      "total_elapsed_time": 40.45209813117981,
      "query_count": 1,
      "queries": [
        {
          "query_index": 0,
          "query": "q65_0",
          "elapsed_time": 27.311443090438843,
          "status": "success"
        }
      ],
      "status": "success"
    },
    {
      "sql_file": "q66",
      "total_elapsed_time": 22.723609924316406,
      "query_count": 1,
      "queries": [
        {
          "query_index": 0,
          "query": "q66_0",
          "elapsed_time": 11.020793914794922,
          "status": "success"
        }
      ],
      "status": "success"
    },
    {
      "sql_file": "q67",
      "total_elapsed_time": 191.35521340370178,
      "query_count": 1,
      "queries": [
        {
          "query_index": 0,
          "query": "q67_0",
          "elapsed_time": 180.86785697937012,
          "status": "success"
        }
      ],
      "status": "success"
    },
    {
      "sql_file": "q68",
      "total_elapsed_time": 18.389883756637573,
      "query_count": 1,
      "queries": [
        {
          "query_index": 0,
          "query": "q68_0",
          "elapsed_time": 4.6519176959991455,
          "status": "success"
        }
      ],
      "status": "success"
    },
    {
      "sql_file": "q69",
      "total_elapsed_time": 19.390760898590088,
      "query_count": 1,
      "queries": [
        {
          "query_index": 0,
          "query": "q69_0",
          "elapsed_time": 9.274848222732544,
          "status": "success"
        }
      ],
      "status": "success"
    },
    {
      "sql_file": "q6",
      "total_elapsed_time": 14.741036653518677,
      "query_count": 1,
      "queries": [
        {
          "query_index": 0,
          "query": "q6_0",
          "elapsed_time": 4.708995819091797,
          "status": "success"
        }
      ],
      "status": "success"
    },
    {
      "sql_file": "q70",
      "total_elapsed_time": 20.053815841674805,
      "query_count": 1,
      "queries": [
        {
          "query_index": 0,
          "query": "q70_0",
          "elapsed_time": 10.098813772201538,
          "status": "success"
        }
      ],
      "status": "success"
    },
    {
      "sql_file": "q71",
      "total_elapsed_time": 17.41480016708374,
      "query_count": 1,
      "queries": [
        {
          "query_index": 0,
          "query": "q71_0",
          "elapsed_time": 7.373473405838013,
          "status": "success"
        }
      ],
      "status": "success"
    },
    {
      "sql_file": "q72",
      "total_elapsed_time": 167.0139446258545,
      "query_count": 1,
      "queries": [
        {
          "query_index": 0,
          "query": "q72_0",
          "elapsed_time": 157.02360939979553,
          "status": "success"
        }
      ],
      "status": "success"
    },
    {
      "sql_file": "q73",
      "total_elapsed_time": 17.48228883743286,
      "query_count": 1,
      "queries": [
        {
          "query_index": 0,
          "query": "q73_0",
          "elapsed_time": 5.075618505477905,
          "status": "success"
        }
      ],
      "status": "success"
    },
    {
      "sql_file": "q74",
      "total_elapsed_time": 40.45848894119263,
      "query_count": 1,
      "queries": [
        {
          "query_index": 0,
          "query": "q74_0",
          "elapsed_time": 30.411683797836304,
          "status": "success"
        }
      ],
      "status": "success"
    },
    {
      "sql_file": "q75",
      "total_elapsed_time": 99.35947585105896,
      "query_count": 1,
      "queries": [
        {
          "query_index": 0,
          "query": "q75_0",
          "elapsed_time": 88.67168641090393,
          "status": "success"
        }
      ],
      "status": "success"
    },
    {
      "sql_file": "q76",
      "total_elapsed_time": 45.27495336532593,
      "query_count": 1,
      "queries": [
        {
          "query_index": 0,
          "query": "q76_0",
          "elapsed_time": 32.734302282333374,
          "status": "success"
        }
      ],
      "status": "success"
    },
    {
      "sql_file": "q77",
      "total_elapsed_time": 20.636494874954224,
      "query_count": 1,
      "queries": [
        {
          "query_index": 0,
          "query": "q77_0",
          "elapsed_time": 8.205379247665405,
          "status": "success"
        }
      ],
      "status": "success"
    },
    {
      "sql_file": "q78",
      "total_elapsed_time": 115.26063346862793,
      "query_count": 1,
      "queries": [
        {
          "query_index": 0,
          "query": "q78_0",
          "elapsed_time": 105.13454723358154,
          "status": "success"
        }
      ],
      "status": "success"
    },
    {
      "sql_file": "q79",
      "total_elapsed_time": 18.541273593902588,
      "query_count": 1,
      "queries": [
        {
          "query_index": 0,
          "query": "q79_0",
          "elapsed_time": 5.7749857902526855,
          "status": "success"
        }
      ],
      "status": "success"
    },
    {
      "sql_file": "q7",
      "total_elapsed_time": 16.932040214538574,
      "query_count": 1,
      "queries": [
        {
          "query_index": 0,
          "query": "q7_0",
          "elapsed_time": 6.3716511726379395,
          "status": "success"
        }
      ],
      "status": "success"
    },
    {
      "sql_file": "q80",
      "total_elapsed_time": 58.34306073188782,
      "query_count": 1,
      "queries": [
        {
          "query_index": 0,
          "query": "q80_0",
          "elapsed_time": 48.06035137176514,
          "status": "success"
        }
      ],
      "status": "success"
    },
    {
      "sql_file": "q81",
      "total_elapsed_time": 23.865105152130127,
      "query_count": 1,
      "queries": [
        {
          "query_index": 0,
          "query": "q81_0",
          "elapsed_time": 12.703283786773682,
          "status": "success"
        }
      ],
      "status": "success"
    },
    {
      "sql_file": "q82",
      "total_elapsed_time": 37.45264911651611,
      "query_count": 1,
      "queries": [
        {
          "query_index": 0,
          "query": "q82_0",
          "elapsed_time": 27.44809079170227,
          "status": "success"
        }
      ],
      "status": "success"
    },
    {
      "sql_file": "q83",
      "total_elapsed_time": 15.70119571685791,
      "query_count": 1,
      "queries": [
        {
          "query_index": 0,
          "query": "q83_0",
          "elapsed_time": 4.622049331665039,
          "status": "success"
        }
      ],
      "status": "success"
    },
    {
      "sql_file": "q84",
      "total_elapsed_time": 18.447118997573853,
      "query_count": 1,
      "queries": [
        {
          "query_index": 0,
          "query": "q84_0",
          "elapsed_time": 8.542226552963257,
          "status": "success"
        }
      ],
      "status": "success"
    },
    {
      "sql_file": "q85",
      "total_elapsed_time": 26.542121171951294,
      "query_count": 1,
      "queries": [
        {
          "query_index": 0,
          "query": "q85_0",
          "elapsed_time": 16.273468017578125,
          "status": "success"
        }
      ],
      "status": "success"
    },
    {
      "sql_file": "q86",
      "total_elapsed_time": 14.968442678451538,
      "query_count": 1,
      "queries": [
        {
          "query_index": 0,
          "query": "q86_0",
          "elapsed_time": 4.6880104541778564,
          "status": "success"
        }
      ],
      "status": "success"
    },
    {
      "sql_file": "q87",
      "total_elapsed_time": 33.70968961715698,
      "query_count": 1,
      "queries": [
        {
          "query_index": 0,
          "query": "q87_0",
          "elapsed_time": 23.79479455947876,
          "status": "success"
        }
      ],
      "status": "success"
    },
    {
      "sql_file": "q88",
      "total_elapsed_time": 43.637757778167725,
      "query_count": 1,
      "queries": [
        {
          "query_index": 0,
          "query": "q88_0",
          "elapsed_time": 33.1466007232666,
          "status": "success"
        }
      ],
      "status": "success"
    },
    {
      "sql_file": "q89",
      "total_elapsed_time": 16.489826202392578,
      "query_count": 1,
      "queries": [
        {
          "query_index": 0,
          "query": "q89_0",
          "elapsed_time": 5.141877889633179,
          "status": "success"
        }
      ],
      "status": "success"
    },
    {
      "sql_file": "q8",
      "total_elapsed_time": 14.451696634292603,
      "query_count": 1,
      "queries": [
        {
          "query_index": 0,
          "query": "q8_0",
          "elapsed_time": 4.254330158233643,
          "status": "success"
        }
      ],
      "status": "success"
    },
    {
      "sql_file": "q90",
      "total_elapsed_time": 19.085740566253662,
      "query_count": 1,
      "queries": [
        {
          "query_index": 0,
          "query": "q90_0",
          "elapsed_time": 8.950004577636719,
          "status": "success"
        }
      ],
      "status": "success"
    },
    {
      "sql_file": "q91",
      "total_elapsed_time": 14.083660125732422,
      "query_count": 1,
      "queries": [
        {
          "query_index": 0,
          "query": "q91_0",
          "elapsed_time": 3.7756388187408447,
          "status": "success"
        }
      ],
      "status": "success"
    },
    {
      "sql_file": "q92",
      "total_elapsed_time": 13.77453875541687,
      "query_count": 1,
      "queries": [
        {
          "query_index": 0,
          "query": "q92_0",
          "elapsed_time": 3.7649166584014893,
          "status": "success"
        }
      ],
      "status": "success"
    },
    {
      "sql_file": "q93",
      "total_elapsed_time": 81.67265820503235,
      "query_count": 1,
      "queries": [
        {
          "query_index": 0,
          "query": "q93_0",
          "elapsed_time": 71.48237776756287,
          "status": "success"
        }
      ],
      "status": "success"
    },
    {
      "sql_file": "q94",
      "total_elapsed_time": 71.79028749465942,
      "query_count": 1,
      "queries": [
        {
          "query_index": 0,
          "query": "q94_0",
          "elapsed_time": 57.9479558467865,
          "status": "success"
        }
      ],
      "status": "success"
    },
    {
      "sql_file": "q95",
      "total_elapsed_time": 112.39780378341675,
      "query_count": 1,
      "queries": [
        {
          "query_index": 0,
          "query": "q95_0",
          "elapsed_time": 100.92545127868652,
          "status": "success"
        }
      ],
      "status": "success"
    },
    {
      "sql_file": "q96",
      "total_elapsed_time": 19.663765907287598,
      "query_count": 1,
      "queries": [
        {
          "query_index": 0,
          "query": "q96_0",
          "elapsed_time": 8.396005392074585,
          "status": "success"
        }
      ],
      "status": "success"
    },
    {
      "sql_file": "q97",
      "total_elapsed_time": 30.314940690994263,
      "query_count": 1,
      "queries": [
        {
          "query_index": 0,
          "query": "q97_0",
          "elapsed_time": 19.639891386032104,
          "status": "success"
        }
      ],
      "status": "success"
    },
    {
      "sql_file": "q98",
      "total_elapsed_time": 15.545313596725464,
      "query_count": 1,
      "queries": [
        {
          "query_index": 0,
          "query": "q98_0",
          "elapsed_time": 4.7795350551605225,
          "status": "success"
        }
      ],
      "status": "success"
    },
    {
      "sql_file": "q99",
      "total_elapsed_time": 21.588258743286133,
      "query_count": 1,
      "queries": [
        {
          "query_index": 0,
          "query": "q99_0",
          "elapsed_time": 11.596024513244629,
          "status": "success"
        }
      ],
      "status": "success"
    },
    {
      "sql_file": "q9",
      "total_elapsed_time": 59.52154564857483,
      "query_count": 1,
      "queries": [
        {
          "query_index": 0,
          "query": "q9_0",
          "elapsed_time": 49.136019468307495,
          "status": "success"
        }
      ],
      "status": "success"
    }
  ]
}